mpsprep/__init__.py
mpsprep/helpers.py
mpsprep/mpsstatepreparation.py
mpsprep-0.1.8.dist-info/LICENSE
mpsprep-0.1.8.dist-info/WHEEL
mpsprep-0.1.8.dist-info/METADATA
mpsprep-0.1.8.dist-info/RECORD
