Metadata-Version: 2.1
Name: mpsprep
Version: 0.1.8
Summary: State preparation for quantum computing using the Matrix Product States approach.
Author: Prithvi Gundlapalli, Junyi Lee
Requires-Python: >=3.7,<3.10
Classifier: Programming Language :: Python :: 3
Classifier: Programming Language :: Python :: 3.7
Classifier: Programming Language :: Python :: 3.8
Classifier: Programming Language :: Python :: 3.9
Requires-Dist: matplotlib (>=3)
Requires-Dist: numpy (>=1.19)
Requires-Dist: scipy (>=1.5)
Requires-Dist: tqdm (>=4.3)
